databasin/__init__.py
databasin/client.py
databasin/datasets.py
databasin/exceptions.py
databasin/jobs.py
databasin/uploads.py
databasin/utils.py
python_databasin-0.6.1.dist-info/LICENSE
python_databasin-0.6.1.dist-info/METADATA
python_databasin-0.6.1.dist-info/WHEEL
python_databasin-0.6.1.dist-info/RECORD
