Metadata-Version: 2.1
Name: python-databasin
Version: 0.6.1
Summary: 
License: BSD-3-Clause
Author: Conservation Biology Institute
Requires-Python: >=3.8,<4.0
Classifier: License :: OSI Approved :: BSD License
Classifier: Programming Language :: Python :: 3
Classifier: Programming Language :: Python :: 3.8
Classifier: Programming Language :: Python :: 3.9
Classifier: Programming Language :: Python :: 3.10
Classifier: Programming Language :: Python :: 3.11
Classifier: Programming Language :: Python :: 3.12
Requires-Dist: python-dateutil (>=2.9.0.post0,<3.0.0)
Requires-Dist: requests (>=2.32.2,<3.0.0)
Requires-Dist: restle (>=0.5.0,<0.6.0)
Requires-Dist: six (>=1.16.0,<2.0.0)
